qtido/__init__.py
qtido-0.9.7.dist-info/METADATA
qtido-0.9.7.dist-info/WHEEL
qtido-0.9.7.dist-info/top_level.txt
qtido-0.9.7.dist-info/RECORD
