Metadata-Version: 2.1
Name: qtido
Version: 0.9.7
Summary: Tracer de figure et d'animatons, pour l'apprentissage de Python, et plus.
Home-page: https://github.com/twitwi/NOT-HERE-qtido/
Author: Rémi Emonet
Author-email: remi-242-e2f8@heeere.com
Classifier: Programming Language :: Python :: 3
Classifier: License :: OSI Approved :: MIT License
Classifier: Operating System :: OS Independent
Requires-Dist: PyQt5
